{
  "hash": "41862551",
  "configHash": "ed3ab5fa",
  "lockfileHash": "43561ff6",
  "browserHash": "930488a8",
  "optimized": {
    "vue": {
      "src": "../../../node_modules/vue/dist/vue.runtime.esm-bundler.js",
      "file": "vue.js",
      "fileHash": "4eb72785",
      "needsInterop": false
    },
    "vitepress > @vue/devtools-api": {
      "src": "../../../node_modules/@vue/devtools-api/lib/esm/index.js",
      "file": "vitepress___@vue_devtools-api.js",
      "fileHash": "5d48c59f",
      "needsInterop": false
    },
    "vitepress > @vueuse/core": {
      "src": "../../../node_modules/@vueuse/core/index.mjs",
      "file": "vitepress___@vueuse_core.js",
      "fileHash": "151a54fe",
      "needsInterop": false
    },
    "element-plus": {
      "src": "../../../node_modules/element-plus/es/index.mjs",
      "file": "element-plus.js",
      "fileHash": "6f912915",
      "needsInterop": false
    }
  },
  "chunks": {
    "chunk-6GA63TRX": {
      "file": "chunk-6GA63TRX.js"
    },
    "chunk-LQ2VYIYD": {
      "file": "chunk-LQ2VYIYD.js"
    }
  }
}